README.rst
setup.cfg
setup.py
django_pipeline_browserify.egg-info/PKG-INFO
django_pipeline_browserify.egg-info/SOURCES.txt
django_pipeline_browserify.egg-info/dependency_links.txt
django_pipeline_browserify.egg-info/requires.txt
django_pipeline_browserify.egg-info/top_level.txt
pipeline_browserify/__init__.py
pipeline_browserify/compiler.py