Metadata-Version: 1.1
Name: django-pipeline-browserify
Version: 0.5.0
Summary: 
